xteam/__init__.py
xteam/__main__.py
xteam/configs.py
xteam/exceptions.py
xteam/loader.py
xteam/storage.py
xteam/version.py
xteam/_misc/__init__.py
xteam/_misc/_assistant.py
xteam/_misc/_decorators.py
xteam/_misc/_supporter.py
xteam/_misc/_wrappers.py
xteam/dB/__init__.py
xteam/dB/_core.py
xteam/dB/afk_db.py
xteam/dB/antiflood_db.py
xteam/dB/asst_fns.py
xteam/dB/asstcmd_db.py
xteam/dB/autoban_db.py
xteam/dB/base.py
xteam/dB/blacklist_chat_db.py
xteam/dB/blacklist_db.py
xteam/dB/botchat_db.py
xteam/dB/broadcast_db.py
xteam/dB/ch_db.py
xteam/dB/dnd_db.py
xteam/dB/echo_db.py
xteam/dB/filestore_db.py
xteam/dB/filter_db.py
xteam/dB/forcesub_db.py
xteam/dB/gban_mute_db.py
xteam/dB/gcast_blacklist_db.py
xteam/dB/greetings_db.py
xteam/dB/logusers_db.py
xteam/dB/mute_db.py
xteam/dB/night_db.py
xteam/dB/notes_db.py
xteam/dB/nsfw_db.py
xteam/dB/pmpermit_db.py
xteam/dB/snips_db.py
xteam/dB/vc_sudos.py
xteam/dB/warn_db.py
xteam/fns/FastTelethon.py
xteam/fns/__init__.py
xteam/fns/admins.py
xteam/fns/custom_markdown.py
xteam/fns/executor.py
xteam/fns/gDrive.py
xteam/fns/helper.py
xteam/fns/info.py
xteam/fns/misc.py
xteam/fns/tools.py
xteam/fns/ytdl.py
xteam/startup/BaseClient.py
xteam/startup/__init__.py
xteam/startup/_database.py
xteam/startup/_extra.py
xteam/startup/connections.py
xteam/startup/funcs.py
xteam/startup/loader.py
xteam/startup/utils.py
xteam-2025.2.25.dist-info/licenses/LICENSE
xteam-2025.2.25.dist-info/METADATA
xteam-2025.2.25.dist-info/WHEEL
xteam-2025.2.25.dist-info/top_level.txt
xteam-2025.2.25.dist-info/RECORD
