Metadata-Version: 2.4
Name: xteam
Version: 2025.2.25
Summary: A Secure and Powerful Python-Telethon Based Library For xteam Userbot.
Home-page: https://github.com/xteam-cloner/xteam
Author: TeamX
Author-email: xteamji@gmail.com
License: GNU AFFERO GENERAL PUBLIC LICENSE (v3)
Project-URL: Bug Tracker, https://github.com/xteam-cloner/xteam/issues
Project-URL: Documentation, https://ultroid.tech
Project-URL: Source Code, https://github.com/xteam-cloner/xteam
Classifier: Programming Language :: Python :: 3
Classifier: Programming Language :: Python :: 3.8
Classifier: Programming Language :: Python :: 3.9
Classifier: Programming Language :: Python :: 3.10
Classifier: Programming Language :: Python :: 3.11
Classifier: Programming Language :: Python :: 3.12
Classifier: License :: OSI Approved :: GNU General Public License v3 (GPLv3)
Classifier: Operating System :: OS Independent
Requires-Python: >3.7, <3.13
License-File: LICENSE
Requires-Dist: redis
Requires-Dist: hiredis
Requires-Dist: python-decouple
Requires-Dist: python-dotenv
Dynamic: author
Dynamic: author-email
Dynamic: classifier
Dynamic: description
Dynamic: description-content-type
Dynamic: home-page
Dynamic: license
Dynamic: license-file
Dynamic: project-url
Dynamic: requires-dist
Dynamic: requires-python
Dynamic: summary
